oleeditor/__init__.py
oleeditor/aboutdialog.py
oleeditor/main.py
oleeditor/oleapp.py
oleeditor/oledocument.py
oleeditor/oleevents.py
oleeditor/oleview.py
oleeditor/olewindow.py
oleeditor/stylehelper.py
oleeditor/version.py
oleeditor-1.0.0.dist-info/LICENSE
oleeditor-1.0.0.dist-info/METADATA
oleeditor-1.0.0.dist-info/WHEEL
oleeditor-1.0.0.dist-info/entry_points.txt
oleeditor-1.0.0.dist-info/top_level.txt
oleeditor-1.0.0.dist-info/RECORD
