Metadata-Version: 2.1
Name: oleeditor
Version: 1.0.0
Summary: An OLE structed storage file editor
Home-page: https://github.com/timxx/oleeditor
Author: Weitian Leung
Author-email: weitianleung@gmail.com
License: MIT
Keywords: ole editor
Platform: any
Classifier: License :: OSI Approved :: MIT License
Classifier: Operating System :: POSIX
Classifier: Operating System :: POSIX :: BSD
Classifier: Operating System :: POSIX :: Linux
Classifier: Operating System :: Microsoft :: Windows
Classifier: Programming Language :: Python :: 3
Requires-Python: >=3
Requires-Dist: PySide2
Requires-Dist: olefile
Requires-Dist: pyhexedit
